setup.py
yamhl/__init__.py
yamhl/makovars.py
yamhl/settings.py
yamhl/utils.py
yamhl/version.py
yamhl/yamhl.py
yamhl.egg-info/PKG-INFO
yamhl.egg-info/SOURCES.txt
yamhl.egg-info/dependency_links.txt
yamhl.egg-info/requires.txt
yamhl.egg-info/top_level.txt